researchhelper/__init__.py
researchhelper/analyse/__init__.py
researchhelper/analyse/distributions.py
researchhelper/datastructures/__init__.py
researchhelper/datastructures/networks.py
researchhelper/datastructures/questionnaires.py
researchhelper/decorators/decorate.py
researchhelper/modeling/__init__.py
researchhelper/modeling/ode.py
researchhelper/optimize/__init__.py
researchhelper/optimize/functionalForms.py
researchhelper/optimize/optimizeOrCalibrate.py
researchhelper/optimize/scoreFunctions.py
researchhelper/processdata/__init__.py
researchhelper/processdata/dataproc.py
researchhelper/processdata/timehandeling.py
researchhelper/visualize/__init__.py
researchhelper/visualize/general_formatting.py
researchhelper/visualize/networks.py
researchhelper-0.1.7.dist-info/WHEEL
researchhelper-0.1.7.dist-info/METADATA
researchhelper-0.1.7.dist-info/RECORD
